LICENCE.txt
README.md
setup.py
Rocket/__init__.py
Rocket/rocket.py
Rocket_FB_1.egg-info/PKG-INFO
Rocket_FB_1.egg-info/SOURCES.txt
Rocket_FB_1.egg-info/dependency_links.txt
Rocket_FB_1.egg-info/top_level.txt