Metadata-Version: 2.1
Name: Rocket_FB_1
Version: 1.0.0
Summary: An awesome package that does something
Home-page: http://pypi.python.org/pypi/Rocket_FB_1/
Author: Fadi
Author-email: benzaimafadi@gmail.com
License: LICENSE.txt
License-File: LICENCE.txt
